get_oodle_lib/__main__.py
get_oodle_lib/common/__init__.py
get_oodle_lib/common/argument_parser.py
get_oodle_lib-0.2.0.dist-info/LICENSE
get_oodle_lib-0.2.0.dist-info/METADATA
get_oodle_lib-0.2.0.dist-info/WHEEL
get_oodle_lib-0.2.0.dist-info/entry_points.txt
get_oodle_lib-0.2.0.dist-info/RECORD
