Metadata-Version: 2.1
Name: get-oodle-lib
Version: 0.2.0
Summary: Get Oodle library for Unreal Engine
Home-page: https://github.com/sehnryr/get-oodle-lib
License: GPL-3.0-or-later
Author: Youn Mélois
Author-email: youn@melois.dev
Requires-Python: >=3.10,<4.0
Classifier: License :: OSI Approved :: GNU General Public License v3 or later (GPLv3+)
Classifier: Programming Language :: Python :: 3
Classifier: Programming Language :: Python :: 3.10
Classifier: Programming Language :: Python :: 3.11
Classifier: Programming Language :: Python :: 3.12
Requires-Dist: parse-commit-gitdeps-xml (>=0.1.0,<0.2.0)
Project-URL: Repository, https://github.com/sehnryr/get-oodle-lib
